[
    {
        "codename": "ux-ui",
        "type": "hum",
        "full_name": "UX/UI Design",
        "short_name": "UX/UI",
        "description": "desc1",
        "instructor": "tmp1",
        "min_overall": 10,
        "max_overall": 60,
        "low_in_group": 15,
        "high_in_group": 25,
        "max_in_group": 30,
        "groups": [
            "year-1",
            "year-2"
        ]
    },
    {
        "codename": "prod-man",
        "type": "hum",
        "full_name": "Basics of Product management",
        "short_name": "Product management",
        "description": "desc2",
        "instructor": "tmp2",
        "min_overall": 10,
        "max_overall": 40,
        "low_in_group": 15,
        "high_in_group": 25,
        "max_in_group": 30,
        "groups": [
            "year-1",
            "year-2"
        ]
    },
    {
        "codename": "psych",
        "type": "hum",
        "full_name": "Psychology of IT-specialist",
        "short_name": "Psychology",
        "description": "desc3",
        "instructor": "tmp3",
        "min_overall": 10,
        "max_overall": 120,
        "low_in_group": 15,
        "high_in_group": 25,
        "max_in_group": 30,
        "groups": [
            "year-1",
            "year-2"
        ]
    },
    {
        "codename": "pub-sp",
        "type": "hum",
        "full_name": "Public Speaking in Business",
        "short_name": "Public Speaking ",
        "description": "desc4",
        "instructor": "tmp4",
        "min_overall": 10,
        "max_overall": 30,
        "low_in_group": 15,
        "high_in_group": 25,
        "max_in_group": 30,
        "groups": [
            "year-1",
            "year-2"
        ]
    },
    {
        "codename": "career-dev",
        "type": "hum",
        "full_name": "Introduction to Career Development for IT-specialist",
        "short_name": "Career Development",
        "description": "desc5",
        "instructor": "tmp5",
        "min_overall": 10,
        "max_overall": 80,
        "low_in_group": 15,
        "high_in_group": 25,
        "max_in_group": 30,
        "groups": [
            "year-1",
            "year-2"
        ]
    },
    {
        "codename": "app-econ",
        "type": "hum",
        "full_name": "Applied Economics: Introduction to IT Entrepreneurship",
        "short_name": "Applied Economics",
        "description": "desc6",
        "instructor": "tmp6",
        "min_overall": 10,
        "max_overall": 30,
        "low_in_group": 15,
        "high_in_group": 25,
        "max_in_group": 30,
        "groups": [
            "year-1"
        ]
    },
    {
        "codename": "desgn-thnk",
        "type": "hum",
        "full_name": "Design Thinking for IT-specialist",
        "short_name": "Design Thinking",
        "description": "desc7",
        "instructor": "tmp7",
        "min_overall": 10,
        "max_overall": 30,
        "low_in_group": 15,
        "high_in_group": 25,
        "max_in_group": 30,
        "groups": [
            "year-1",
            "year-2"
        ]
    },
    {
        "codename": "pers-eff",
        "type": "hum",
        "full_name": "Personal Efficiency skills",
        "short_name": "Personal Efficiency",
        "description": "desc8",
        "instructor": "tmp8",
        "min_overall": 10,
        "max_overall": 160,
        "low_in_group": 15,
        "high_in_group": 25,
        "max_in_group": 30,
        "groups": [
            "year-1",
            "year-2"
        ]
    },
    {
        "codename": "carerr-lead",
        "type": "hum",
        "full_name": "Career and Leadership",
        "short_name": "Career and Leadership",
        "description": "desc9",
        "instructor": "tmp9",
        "min_overall": 10,
        "max_overall": 30,
        "low_in_group": 15,
        "high_in_group": 25,
        "max_in_group": 30,
        "groups": [
            "year-1",
            "year-2"
        ]
    },
    {
        "codename": "tech-startup",
        "type": "hum",
        "full_name": "Tech Startup Design",
        "short_name": "Tech Startup",
        "description": "desc10",
        "instructor": "tmp10",
        "min_overall": 10,
        "max_overall": 30,
        "low_in_group": 15,
        "high_in_group": 25,
        "max_in_group": 30,
        "groups": [
            "year-1"
        ]
    },
    {
        "codename": "reading",
        "type": "hum",
        "full_name": "Reading skills for IT specialist",
        "short_name": "Reading skills",
        "description": "desc11",
        "instructor": "tmp11",
        "min_overall": 10,
        "max_overall": 30,
        "low_in_group": 10,
        "high_in_group": 25,
        "max_in_group": 30,
        "groups": [
            "year-1",
            "year-2"
        ]
    },
    {
        "codename": "ceo-kit",
        "type": "hum",
        "full_name": "Startup CEO Toolkit",
        "short_name": "Startup CEO",
        "description": "desc12",
        "instructor": "tmp12",
        "min_overall": 10,
        "max_overall": 30,
        "low_in_group": 15,
        "high_in_group": 25,
        "max_in_group": 30,
        "groups": [
            "year-1",
            "year-2"
        ]
    },
    {
        "codename": "cult-com",
        "type": "hum",
        "full_name": "Cross-cultural communication",
        "short_name": "Cross-cultural communication",
        "description": "desc13",
        "instructor": "tmp13",
        "min_overall": 10,
        "max_overall": 30,
        "low_in_group": 10,
        "high_in_group": 25,
        "max_in_group": 30,
        "groups": [
            "year-1"
        ]
    },
    {
        "codename": "social-entr",
        "type": "hum",
        "full_name": "Social Entrepreneurship",
        "short_name": "Social Entrepreneurship",
        "description": "desc14",
        "instructor": "tmp14",
        "min_overall": 10,
        "max_overall": 30,
        "low_in_group": 10,
        "high_in_group": 25,
        "max_in_group": 30,
        "groups": [
            "year-1",
            "year-2"
        ]
    },
    {
        "codename": "it-team",
        "type": "hum",
        "full_name": "How to build an IT team",
        "short_name": "Build IT team",
        "description": "desc15",
        "instructor": "tmp15",
        "min_overall": 10,
        "max_overall": 30,
        "low_in_group": 10,
        "high_in_group": 25,
        "max_in_group": 30,
        "groups": [
            "year-2"
        ]
    },
    {
        "codename": "it-buisness",
        "type": "hum",
        "full_name": "Intro to IT business strategies",
        "short_name": "Into to buisness",
        "description": "desc16",
        "instructor": "tmp16",
        "min_overall": 10,
        "max_overall": 30,
        "low_in_group": 10,
        "high_in_group": 25,
        "max_in_group": 30,
        "groups": [
            "year-2"
        ]
    }
]